diemsim/__init__.py
diemsim/DIEM.py
diemsim-0.0.8.dist-info/LICENSE
diemsim-0.0.8.dist-info/METADATA
diemsim-0.0.8.dist-info/WHEEL
diemsim-0.0.8.dist-info/RECORD
