Metadata-Version: 2.3
Name: diemsim
Version: 0.0.8
Summary: A Python Library Implementing Dimension Insensitive Euclidean Metric (DIEM)
License: MIT
Author: Boddu Sri Pavan
Author-email: boddusripavan111@gmail.com
Requires-Python: >=3.11
Classifier: Programming Language :: Python :: 3
Classifier: License :: OSI Approved :: MIT License
Classifier: Operating System :: OS Independent
Classifier: Intended Audience :: Science/Research
Classifier: Topic :: Scientific/Engineering :: Mathematics
Requires-Dist: numpy (>=1.23.5,<2.0.0)
Project-URL: Homepage, https://github.com/BodduSriPavan-111/diemsim
Project-URL: Issues, https://github.com/BodduSriPavan-111/diemsim/issues
Project-URL: Repository, https://github.com/BodduSriPavan-111/diemsim
